verilog/aaron_james_toUpper.v
`timescale 1ns/1ps

module toUpper(
    input  wire [7:0] in,
    output wire [7:0] out
);
    wire a1_out, a2_out, a3_out, a4_out;
    wire ni6, ni5, ni4, ni3, ni2, ni1, ni7, ni0;
    
    not #5 n7 (ni7, in[7]);
    not #5  n6 (ni6, in[6]);
    not #5 n5 (ni5, in[5]);
    not #5  n4 (ni4, in[4]);
    not #5  n3 (ni3, in[3]);
    not #5  n2 (ni2, in[2]);
    not #5  n1 (ni1, in[1]);
    not #5 n0 (ni0, in[0]);


    and #10  a1 (a1_out, ni7,ni6,in[5]);
    and #10 a2 (a2_out, in[7], in[5]);
    and #10 a3 (a3_out, ni7,in[6], in[5],  ni4, ni3, ni2, ni1,ni0);
    and #10 a4(a4_out, ni7, in[5], in[6], in[4], in[3], in[2]);
    and #10 a5(a5_out,ni7, in[6], in[5], in[4], in[3], ni2, in[1], in[0]);



    
    or #10  o1 (out[5], a1_out, a2_out, a3_out, a4_out, a5_out);



    buf #4 b0 (out[0], in[0]);
    buf #4 b1 (out[1], in[1]);
    buf #4 b2 (out[2], in[2]);
    buf #4 b3 (out[3], in[3]);
    buf #4 b4 (out[4], in[4]);
    buf #4 b6 (out[6], in[6]);
    buf #4 b7 (out[7], in[7]);

endmodule

verilog/aaron_james_toUpper_tb.v

`timescale 1ns/1ps

module toUpper_tb;
	reg [7:0] in;
	wire [7:0] out;

	// Instantiate DUT
	toUpper dut (.in(in), .out(out));

	// Test vectors: decimal, binary (for readability), comment (symbol)
	reg [7:0] vectors [0:18];

	integer i;

	initial begin
		// Fill vectors
		vectors[0]  = 8'd40;   // 00101000  '('
		vectors[1]  = 8'd72;   // 01001000  'H'
		vectors[2]  = 8'd183;  // 10110111  '·'
		vectors[3]  = 8'd131;  // 10000011  'ƒ'
		vectors[4]  = 8'd124;  // 01111100  '|'
		vectors[5]  = 8'd20;   // 00010100  'DC4'
		vectors[6]  = 8'd235;  // 11101011  'ë'
		vectors[7]  = 8'd97;   // 01100001  'a'
		vectors[8]  = 8'd65;   // 01000001  'A'
		vectors[9]  = 8'd122;  // 01111010  'z'
		vectors[10] = 8'd71;   // 01000111  'G'
		vectors[11] = 8'd109;  // 01101101  'm'
		vectors[12] = 8'd146;  // 10010010  '\'' (note: 146 is non-ASCII printable here)
		vectors[13] = 8'd48;   // 00110000  '0'
		vectors[14] = 8'd207;  // 11001111  'Ï'
		vectors[15] = 8'd58;   // 00111010  ':'
		vectors[16] = 8'd123;  // 01111011  '{'
		vectors[17] = 8'd148;  // 10000100  '”'
		vectors[18] = 8'd127;  // 01111111  'DEL'

		// Start VCD dump
		$dumpfile("toUpper_tb.vcd");
		$dumpvars(0, toUpper_tb);

		// Header for human-readable output
		$display("time ns |  in(dec) in(bin)  in(char) | out(dec) out(bin) out(char)");
		$display("---------------------------------------------------------------------");

		// Apply each vector and display results
		for (i = 0; i < 19; i = i + 1) begin
			in = vectors[i];
			#25.1; // wait for propagation
			$display("%4dns | %7d %b %s | %7d %b %s", $time, in, in, format_char(in), out, out, format_char(out));
		end

		#20;
		$display("Test complete.");
		$finish;
	end

	// Function to format a byte as printable char or '.' if non-printable
	function [8*4:1] format_char; // return up to 4 chars (enough for annotations)
		input [7:0] b;
		begin
			if (b >= 8'd32 && b <= 8'd126) begin
				format_char = {1'b0, b};
			end else begin
				// return a short label for a few known control codes, else '.'
				case (b)
					8'd127: format_char = "DEL";
					8'd20:  format_char = "DC4";
					default: format_char = ".";
				endcase
			end
		end
	endfunction

endmodule

verilog/toUpper_tb.vcd
$date
	Mon Nov  3 17:12:43 2025
$end
$version
	Icarus Verilog
$end
$timescale
	1ps
$end
$scope module toUpper_tb $end
$var wire 8 ! out [7:0] $end
$var reg 8 " in [7:0] $end
$var integer 32 # i [31:0] $end
$scope function format_char $end
$var reg 8 $ b [7:0] $end
$upscope $end
$scope module dut $end
$var wire 1 % a1_out $end
$var wire 1 & a2_out $end
$var wire 1 ' a3_out $end
$var wire 1 ( a4_out $end
$var wire 1 ) a5_out $end
$var wire 8 * in [7:0] $end
$var wire 1 + ni0 $end
$var wire 1 , ni1 $end
$var wire 1 - ni2 $end
$var wire 1 . ni3 $end
$var wire 1 / ni4 $end
$var wire 1 0 ni5 $end
$var wire 1 1 ni6 $end
$var wire 1 2 ni7 $end
$var wire 8 3 out [7:0] $end
$upscope $end
$upscope $end
$enddefinitions $end
$comment Show the parameter values. $end
$dumpall
$end
#0
$dumpvars
bx 3
x2
x1
x0
x/
x.
x-
x,
x+
b101000 *
x)
x(
x'
x&
x%
bx $
b0 #
b101000 "
bx !
$end
#4000
b0x01000 !
b0x01000 3
#5000
12
11
00
1/
0.
1-
1,
1+
#10000
0'
0(
0)
0&
#15000
1%
#25000
b101000 !
b101000 3
#25100
b1001000 "
b1001000 *
b1 #
b101000 $
#29100
b1101000 !
b1101000 3
#30100
01
10
#35100
0%
#45100
b1001000 !
b1001000 3
#50200
b10110111 "
b10110111 *
b10 #
b1001000 $
#54200
b10010111 !
b10010111 3
#55200
02
11
00
0/
1.
0-
0,
0+
#60200
1&
#70200
b10110111 !
b10110111 3
#75300
b10000011 "
b10000011 *
b11 #
b10110111 $
#79300
b10100011 !
b10100011 3
#80300
10
1/
1-
#85300
0&
#95300
b10000011 !
b10000011 3
#100400
b1111100 "
b1111100 *
b100 #
b10000011 $
#104400
b1011100 !
b1011100 3
#105400
12
01
00
0/
0.
0-
1,
1+
#115400
1(
#125400
b1111100 !
b1111100 3
#125500
b10100 "
b10100 *
b101 #
b1111100 $
#129500
b110100 !
b110100 3
#130500
11
10
1.
#135500
0(
#145500
b10100 !
b10100 3
#150600
b11101011 "
b11101011 *
b110 #
b10100 $
#154600
b11001011 !
b11001011 3
#155600
02
01
00
1/
0.
1-
0,
0+
#160600
1&
#170600
b11101011 !
b11101011 3
#175700
b1100001 "
b1100001 *
b111 #
b11101011 $
#179700
b1100001 !
b1100001 3
#180700
12
1.
1,
#185700
0&
#195700
b1000001 !
b1000001 3
#200800
b1000001 "
b1000001 *
b1000 #
b1000001 $
#205800
10
#225900
b1111010 "
b1111010 *
b1001 #
#229900
b1011010 !
b1011010 3
#230900
00
0/
0.
0,
1+
#251000
b1000111 "
b1000111 *
b1010 #
b1011010 $
#255000
b1000111 !
b1000111 3
#256000
10
1/
1.
0-
0+
#276100
b1101101 "
b1101101 *
b1011 #
b1000111 $
#280100
b1001101 !
b1001101 3
#281100
00
0.
1,
#301200
b10010010 "
b10010010 *
b1100 #
b1001101 $
#305200
b10010010 !
b10010010 3
#306200
02
11
10
0/
1.
1-
0,
1+
#326300
b110000 "
b110000 *
b1101 #
b10010010 $
#330300
b10000 !
b10000 3
#331300
12
00
1,
#341300
1%
#351300
b110000 !
b110000 3
#351400
b11001111 "
b11001111 *
b1110 #
b110000 $
#355400
b11101111 !
b11101111 3
#356400
02
01
10
1/
0.
0-
0,
0+
#361400
0%
#371400
b11001111 !
b11001111 3
#376500
b111010 "
b111010 *
b1111 #
b11001111 $
#380500
b11010 !
b11010 3
#381500
12
11
00
0/
1-
1+
#391500
1%
#401500
b111010 !
b111010 3
#401600
b1111011 "
b1111011 *
b10000 #
b111010 $
#405600
b1111011 !
b1111011 3
#406600
01
0+
#411600
1)
#416600
0%
#426700
b10010100 "
b10010100 *
b10001 #
b1111011 $
#430700
b10110100 !
b10110100 3
#431700
02
11
10
1.
0-
1,
1+
#436700
0)
#446700
b10010100 !
b10010100 3
#451800
b1111111 "
b1111111 *
b10010 #
b10010100 $
#455800
b1011111 !
b1011111 3
#456800
12
01
00
0.
0,
0+
#466800
1(
#476800
b1111111 !
b1111111 3
#476900
b10011 #
b1111111 $
